streamlit_oekaki_component/__init__.py
streamlit_oekaki_component/frontend/index.html
streamlit_oekaki_component/frontend/main.js
streamlit_oekaki_component/frontend/streamlit-component-lib.js
streamlit_oekaki_component/frontend/style.css
streamlit_oekaki_component-0.1.2.dist-info/LICENSE
streamlit_oekaki_component-0.1.2.dist-info/METADATA
streamlit_oekaki_component-0.1.2.dist-info/WHEEL
streamlit_oekaki_component-0.1.2.dist-info/top_level.txt
streamlit_oekaki_component-0.1.2.dist-info/RECORD
