Metadata-Version: 2.1
Name: streamlit-oekaki-component
Version: 0.1.2
Summary: A Streamlit component for simple freehand drawing. It allows users to draw freely on a canvas and integrates seamlessly with Streamlit apps.
Home-page: https://github.com/Gohei/streamlit_oekaki_component
Author: Gohei Kusumi
Author-email: gohei.kusumi@gmail.com
Classifier: Programming Language :: Python :: 3
Classifier: License :: OSI Approved :: MIT License
Classifier: Operating System :: OS Independent
Requires-Python: >=3.6
License-File: LICENSE
